syaml/__init__.py
syaml/interfaces.py
syaml/settings.py
syaml/syaml.py
syaml/commands/__init__.py
syaml/commands/render.py
syaml/tests/__init__.py
syaml/tests/syaml_test.yaml
syaml/tests/test_ok.py
syaml/tests/test_syaml.py
syaml-2.0.dist-info/LICENSE
syaml-2.0.dist-info/METADATA
syaml-2.0.dist-info/WHEEL
syaml-2.0.dist-info/entry_points.txt
syaml-2.0.dist-info/top_level.txt
syaml-2.0.dist-info/RECORD
