Metadata-Version: 2.1
Name: syaml
Version: 2.0
Summary: YAML parser that environment variable is expanded
Home-page: UNKNOWN
Author: symdon
Author-email: 8707279+TakesxiSximada@users.noreply.github.com
Maintainer: symdon
Maintainer-email: 8707279+TakesxiSximada@users.noreply.github.com
License: AGPL-3.0-or-later
Keywords: YAML
Platform: UNKNOWN
Classifier: Development Status :: 5 - Production/Stable
Classifier: License :: OSI Approved :: Apache Software License
Classifier: Programming Language :: Python
Classifier: Programming Language :: Python :: 3
Classifier: Programming Language :: Python :: 3.10
Classifier: Programming Language :: Python :: 3.6
Classifier: Programming Language :: Python :: 3.7
Classifier: Programming Language :: Python :: 3.8
Classifier: Programming Language :: Python :: 3.9
Classifier: Topic :: Software Development
Requires-Python: >=3.6
License-File: LICENSE
Requires-Dist: PyYAML
Requires-Dist: jumon
Requires-Dist: mako
Requires-Dist: six
Requires-Dist: zope.component
Requires-Dist: zope.interface
Provides-Extra: packaging
Requires-Dist: build ; extra == 'packaging'
Requires-Dist: setuptools ; extra == 'packaging'
Requires-Dist: twine ; extra == 'packaging'
Requires-Dist: wheel ; extra == 'packaging'
Provides-Extra: testing
Requires-Dist: flake8 ; extra == 'testing'
Requires-Dist: pytest ; extra == 'testing'
Requires-Dist: tox ; extra == 'testing'
